[
    {
        "id": "p10000",
        "pid": "0",
        "path": "\/dashboard",
        "name": "Dashboard",
        "order": 1,
        "icon": "icon-dashboard",
        "locale": "menu.server.dashboard",
        "requiresAuth": true,
        "filePath": "dashboard",
        "super": true,
        "admin": true,
        "author": true,
        "isDelete": false
    },
    {
        "id": "p10001",
        "pid": "p10000",
        "path": "\/dashboard\/workplace",
        "name": "Workplace",
        "order": 1,
        "icon": "",
        "locale": "menu.server.workplace",
        "requiresAuth": true,
        "filePath": "workplace",
        "super": true,
        "admin": true,
        "author": true,
        "isDelete": false
    },
    {
        "id": "p188880",
        "pid": "0",
        "path": "\/system",
        "name": "System",
        "order": 188,
        "icon": "icon-settings",
        "locale": "menu.server.system",
        "requiresAuth": true,
        "filePath": "system",
        "super": true,
        "admin": true,
        "author": false,
        "isDelete": false
    },
    {
        "id": "p188881",
        "pid": "p188880",
        "path": "\/system\/userManage",
        "name": "UserManage",
        "order": 188,
        "icon": "",
        "locale": "menu.server.userManage",
        "requiresAuth": true,
        "filePath": "UserManage",
        "super": true,
        "admin": false,
        "author": false,
        "isDelete": false
    },
    {
        "id": "p188882",
        "pid": "p188880",
        "path": "\/system\/menuManage",
        "name": "MenuManage",
        "order": 188,
        "icon": "",
        "locale": "menu.server.menuManage",
        "requiresAuth": true,
        "filePath": "MenuManage",
        "super": true,
        "admin": true,
        "author": false,
        "isDelete": false
    }
]